Gempa_Terkini/__init__.py
earthquake_INA-0.0.1.dist-info/LICENSE
earthquake_INA-0.0.1.dist-info/METADATA
earthquake_INA-0.0.1.dist-info/WHEEL
earthquake_INA-0.0.1.dist-info/top_level.txt
earthquake_INA-0.0.1.dist-info/RECORD
