Metadata-Version: 2.1
Name: earthquake-INA
Version: 0.0.1
Summary: This is package will get the latest earthquake from BMKG|Meteorological Climatological and Geophysical Agency
Home-page: https://github.com/Xavista/Latest-Indonesiaearthquake
Author: Ilham sapista 
Author-email: ilham.sapista@gmail.com
Classifier: Programming Language :: Python :: 3
Classifier: License :: OSI Approved :: GNU General Public License v3 (GPLv3)
Classifier: Operating System :: OS Independent
Requires-Python: >=3.6
License-File: LICENSE
